torch_mir_eval/__init__.py
torch_mir_eval/_version.py
torch_mir_eval/batch_separation.py
torch_mir_eval/separation.py
torch_mir_eval/toeplitz.py
torch_mir_eval-0.4.dist-info/LICENSE
torch_mir_eval-0.4.dist-info/METADATA
torch_mir_eval-0.4.dist-info/WHEEL
torch_mir_eval-0.4.dist-info/top_level.txt
torch_mir_eval-0.4.dist-info/RECORD
