Metadata-Version: 2.1
Name: torch-mir-eval
Version: 0.4
Summary: Mir_eval package ported to pytorch 
Home-page: https://github.com/JuanFMontesinos/torch_mir_eval
Author: Juan Montesinos
Author-email: juanfelipe.montesinos@upf.edu
License: UNKNOWN
Platform: UNKNOWN
Classifier: Programming Language :: Python :: 3
Requires-Dist: torch (>=1.9)
